{
  "key": "solarized-dark",
  "display_name": "Solarized Dark",
  "scale": 1.0,
  "rounding": { "Window": 4.0, "Frame": 3.0, "Grab": 3.0, "Tab": 3.0, "Popup": 4.0 },
  "padding": { "Window": [8,8], "Frame": [8,5], "Item": [8,6], "Inner": [6,4] },
  "colors": {
    "Text": "#EAEAEA",
    "WindowBg": "#0E1111",
    "ChildBg":  "#111417",
    "PopupBg":  "#0D0F10F0",
    "Border":   "#2C3440",
    "FrameBg":  "#1C232B",
    "FrameBgHovered": "#26303A",
    "FrameBgActive":  "#2E3944",
    "TitleBg":  "#14181C",
    "TitleBgActive": "#14181C",
    "MenuBarBg":"#14181C",
    "ScrollbarGrab":"#56606A",
    "Button":"#27323B",
    "ButtonHovered":"#31404C",
    "ButtonActive":"#3A4C59",
    "Header":"#25313A",
    "HeaderHovered":"#2E3C47",
    "HeaderActive":"#344550",
    "Separator":"#2C3440",
    "Tab":"#20292F",
    "TabHovered":"#2A353D",
    "TabActive":"#26313A",
    "TabUnfocused":"#1D252B",
    "TabUnfocusedActive":"#232C33",
    "NavHighlight":"#268BD2",
    "DragDropTarget":"#2AA198",
    "TextSelectedBg":"#2C3440C0",
    "TableHeaderBg":"#222B33",
    "TableBorderStrong":"#2C3440",
    "TableBorderLight":"#232B35"
  }
}
